CHANGES.txt
README.txt
kick-i18ndude.sh
setup.cfg
setup.py
jyu/__init__.py
jyu.portalview.egg-info/PKG-INFO
jyu.portalview.egg-info/SOURCES.txt
jyu.portalview.egg-info/dependency_links.txt
jyu.portalview.egg-info/entry_points.txt
jyu.portalview.egg-info/namespace_packages.txt
jyu.portalview.egg-info/not-zip-safe
jyu.portalview.egg-info/requires.txt
jyu.portalview.egg-info/top_level.txt
jyu/portalview/README.txt
jyu/portalview/__init__.py
jyu/portalview/config.py
jyu/portalview/configure.zcml
jyu/portalview/interfaces.py
jyu/portalview/version.txt
jyu/portalview/browser/__init__.py
jyu/portalview/browser/configure.zcml
jyu/portalview/browser/menubar.pt
jyu/portalview/browser/portalview.pt
jyu/portalview/browser/portalview.py
jyu/portalview/browser/viewlets.py
jyu/portalview/browser/boxes/__init__.py
jyu/portalview/browser/boxes/atct_boxview.pt
jyu/portalview/browser/boxes/atct_document_boxview.pt
jyu/portalview/browser/boxes/atct_topic_boxview.pt
jyu/portalview/browser/boxes/boxes.py
jyu/portalview/browser/boxes/configure.zcml
jyu/portalview/browser/images/box_bg.png
jyu/portalview/browser/images/box_bullet.gif
jyu/portalview/browser/images/box_feed_icon.gif
jyu/portalview/browser/images/column_icon.png
jyu/portalview/browser/images/menubar_bullet.gif
jyu/portalview/browser/images/pencil_icon.gif
jyu/portalview/browser/images/portalview_icon.png
jyu/portalview/browser/styles/menubar.css
jyu/portalview/browser/styles/portalview.css
jyu/portalview/content/__init__.py
jyu/portalview/content/configure.zcml
jyu/portalview/content/portalview.py
jyu/portalview/content/portalviewcolumnfolder.py
jyu/portalview/content/schemata.py
jyu/portalview/content/validators.py
jyu/portalview/i18n/plone-fi.po
jyu/portalview/i18n/plone.pot
jyu/portalview/locales/jyu.portalview.pot
jyu/portalview/locales/fi/LC_MESSAGES/jyu.portalview.plonelocales.po
jyu/portalview/locales/fi/LC_MESSAGES/jyu.portalview.po
jyu/portalview/profiles/__init__.py
jyu/portalview/profiles/default/cssregistry.xml
jyu/portalview/profiles/default/factorytool.xml
jyu/portalview/profiles/default/metadata.xml
jyu/portalview/profiles/default/types.xml
jyu/portalview/profiles/default/viewlets.xml
jyu/portalview/profiles/default/types/Portal_View.xml
jyu/portalview/profiles/default/types/Portal_View_Column_Folder.xml
