Metadata-Version: 1.0
Name: jyu.portalview
Version: 1.0.3
Summary: A content type, which displays content in a portal like aggregating view
Home-page: http://svn.plone.org/svn/collective/jyu.portalview
Author: Jukka Ojaniemi
Author-email: jukka.ojaniemi@jyu.fi
License: GPL
Keywords: plone content portal view
Platform: UNKNOWN
Classifier: Framework :: Plone
Classifier: Intended Audience :: Developers
Classifier: Topic :: Software Development :: Libraries :: Python Modules
Classifier: License :: OSI Approved :: GNU General Public License (GPL)
